DuckDuckGoImages.py
DuckDuckGoImages-2.0.8.dist-info/LICENSE.txt
DuckDuckGoImages-2.0.8.dist-info/METADATA
DuckDuckGoImages-2.0.8.dist-info/WHEEL
DuckDuckGoImages-2.0.8.dist-info/top_level.txt
DuckDuckGoImages-2.0.8.dist-info/RECORD
