Metadata-Version: 2.1
Name: DuckDuckGoImages
Version: 2.0.8
Summary: Download images from DuckDuckGo
Home-page: https://github.com/JorgePoblete/DuckDuckGoImages
Author: koke
Author-email: jpobleteriquelme@gmail.com
License: UNKNOWN
Platform: UNKNOWN
Classifier: Programming Language :: Python :: 3
Classifier: License :: OSI Approved :: MIT License
Classifier: Operating System :: OS Independent
Requires-Python: >=3.6
License-File: LICENSE.txt
Requires-Dist: requests (>=2.24.0)
Requires-Dist: joblib (>=0.16.0)
Requires-Dist: Pillow (>=2.2.1)
Requires-Dist: tqdm (>=4.62.3)
Provides-Extra: dev
Requires-Dist: pytest (>=3.7) ; extra == 'dev'
